fatpacker/__init__.py
fatpacker/cli.py
fatpacker-0.1.data/scripts/fatpacker
fatpacker-0.1.dist-info/LICENSE
fatpacker-0.1.dist-info/METADATA
fatpacker-0.1.dist-info/WHEEL
fatpacker-0.1.dist-info/top_level.txt
fatpacker-0.1.dist-info/RECORD
