Metadata-Version: 2.1
Name: fatpacker
Version: 0.1
Summary: package python applications as standalone scripts
Home-page: https://github.com/f0rk/fatpacker
Author: Ryan P. Kelly
Author-email: ryan@ryankelly.us
License: UNKNOWN
Platform: UNKNOWN
Classifier: Development Status :: 3 - Alpha
Classifier: Environment :: Console
Classifier: Intended Audience :: Developers
Classifier: Intended Audience :: System Administrators
Classifier: License :: OSI Approved :: MIT License
Classifier: Operating System :: MacOS :: MacOS X
Classifier: Operating System :: POSIX
Classifier: Programming Language :: Python :: 3
Classifier: Topic :: Software Development :: Build Tools
Classifier: Topic :: Software Development :: Libraries
Requires-Dist: spindrift
